[
  {
	"SkillID" :1,
	"Name" : "skill1",
	"AttackParam" : 1.5,
	"AttackDistance" : 5,
	"CD" : 1000,
	"Type" : 1,
	"TotalWave" : 1,
	"WaveInterval" : "",
	"DamageType" : 1,
	"RangeParams" : "3",
	"TargetNum" : 5,
	"SelfBuffs" : "",
	"TargetBuffs" : ""
  },
  {
	"SkillID" :2,
	"Name" : "skill2",
	"AttackParam" : 2,
	"AttackDistance" : 5,
	"CD" : 5000,
	"Type" : 0,
	"TotalWave" : 2,
	"WaveInterval" : "300",
	"DamageType" : 2,
	"RangeParams" : "3",
	"TargetNum" : 5,
	"SelfBuffs" : "",
	"TargetBuffs" : ""
  }
]